geo_ez/__init__.py
geo_ez/admin.py
geo_ez/apps.py
geo_ez/constants.py
geo_ez/data_functions.py
geo_ez/models.py
geo_ez/tests.py
geo_ez/urls.py
geo_ez/us_census_class.py
geo_ez/usps_class.py
geo_ez/utility_functions.py
geo_ez/views.py
geo_ez/management/__init__.py
geo_ez/management/commands/__init__.py
geo_ez/management/commands/import-postal-codes.py
geo_ez/management/commands/test-radius.py
geo_ez/migrations/0001_initial.py
geo_ez/migrations/0002_streetaddress.py
geo_ez/migrations/__init__.py
geo_ez-0.1.5.dist-info/LICENSE
geo_ez-0.1.5.dist-info/METADATA
geo_ez-0.1.5.dist-info/WHEEL
geo_ez-0.1.5.dist-info/top_level.txt
geo_ez-0.1.5.dist-info/RECORD
