Metadata-Version: 2.1
Name: geo-ez
Version: 0.1.5
Summary: Tools for building geographically aware django apps, without needing to install a real GIS backend.
Home-page: https://github.com/avryhof/geo_ez
Author: Amos Vryhof
Author-email: amos@vryhofresearch.com
License: MIT
Platform: UNKNOWN
Classifier: Development Status :: 5 - Production/Stable
Classifier: Intended Audience :: Developers
Classifier: License :: OSI Approved :: MIT License
Classifier: Programming Language :: Python :: 3
Requires-Dist: bleach
Requires-Dist: django
Requires-Dist: future
Requires-Dist: requests
Requires-Dist: xmltodict
